pytodomd/__init__.py
pytodomd/cli.py
pytodomd-0.0.1.dist-info/METADATA
pytodomd-0.0.1.dist-info/WHEEL
pytodomd-0.0.1.dist-info/entry_points.txt
pytodomd-0.0.1.dist-info/top_level.txt
pytodomd-0.0.1.dist-info/RECORD
