Metadata-Version: 2.1
Name: pytodomd
Version: 0.0.1
Summary: UNKNOWN
Home-page: UNKNOWN
Author: Maciej Lorenc
Author-email: lorencmaciek@gmail.com
License: UNKNOWN
Platform: UNKNOWN
Requires-Dist: click
